{"theater-posture:stale:v4":{"value":{"postures":[{"theaterId":"iran-theater","theaterName":"Iran Theater","shortName":"IRAN","targetNation":"Iran","fighters":0,"tankers":0,"awacs":0,"reconnaissance":0,"transport":0,"bombers":0,"drones":0,"unknown":4,"totalAircraft":4,"destroyers":0,"frigates":0,"carriers":0,"submarines":0,"patrol":0,"auxiliaryVessels":0,"totalVessels":0,"byOperator":{"unknown":4},"postureLevel":"normal","strikeCapable":false,"trend":"stable","changePercent":0,"summary":"4 other","headline":"Normal activity - Iran Theater","centerLat":31,"centerLon":47.5,"bounds":{"north":42,"south":20,"east":65,"west":30}},{"theaterId":"taiwan-theater","theaterName":"Taiwan Strait","shortName":"TAIWAN","targetNation":"Taiwan","fighters":0,"tankers":0,"awacs":0,"reconnaissance":0,"transport":0,"bombers":0,"drones":0,"unknown":0,"totalAircraft":0,"destroyers":0,"frigates":0,"carriers":0,"submarines":0,"patrol":0,"auxiliaryVessels":0,"totalVessels":0,"byOperator":{},"postureLevel":"normal","strikeCapable":false,"trend":"stable","changePercent":0,"summary":"No military aircraft","headline":"Normal activity - Taiwan Strait","centerLat":24,"centerLon":122.5,"bounds":{"north":30,"south":18,"east":130,"west":115}},{"theaterId":"baltic-theater","theaterName":"Baltic Theater","shortName":"BALTIC","targetNation":null,"fighters":0,"tankers":0,"awacs":0,"reconnaissance":0,"transport":0,"bombers":0,"drones":0,"unknown":2,"totalAircraft":2,"destroyers":0,"frigates":0,"carriers":0,"submarines":0,"patrol":0,"auxiliaryVessels":0,"totalVessels":0,"byOperator":{"unknown":2},"postureLevel":"normal","strikeCapable":false,"trend":"stable","changePercent":0,"summary":"2 other","headline":"Normal activity - Baltic Theater","centerLat":58.5,"centerLon":21,"bounds":{"north":65,"south":52,"east":32,"west":10}},{"theaterId":"blacksea-theater","theaterName":"Black Sea","shortName":"BLACK SEA","targetNation":null,"fighters":0,"tankers":0,"awacs":0,"reconnaissance":0,"transport":0,"bombers":0,"drones":0,"unknown":1,"totalAircraft":1,"destroyers":0,"frigates":0,"carriers":0,"submarines":0,"patrol":0,"auxiliaryVessels":0,"totalVessels":0,"byOperator":{"unknown":1},"postureLevel":"normal","strikeCapable":false,"trend":"stable","changePercent":0,"summary":"1 other","headline":"Normal activity - Black Sea","centerLat":44,"centerLon":34,"bounds":{"north":48,"south":40,"east":42,"west":26}},{"theaterId":"korea-theater","theaterName":"Korean Peninsula","shortName":"KOREA","targetNation":"North Korea","fighters":0,"tankers":0,"awacs":0,"reconnaissance":0,"transport":0,"bombers":0,"drones":0,"unknown":5,"totalAircraft":5,"destroyers":0,"frigates":0,"carriers":0,"submarines":0,"patrol":0,"auxiliaryVessels":0,"totalVessels":0,"byOperator":{"unknown":5},"postureLevel":"elevated","strikeCapable":false,"trend":"stable","changePercent":0,"summary":"5 other","headline":"Elevated military activity - Korean Peninsula","centerLat":38,"centerLon":128,"bounds":{"north":43,"south":33,"east":132,"west":124}},{"theaterId":"south-china-sea","theaterName":"South China Sea","shortName":"SCS","targetNation":null,"fighters":0,"tankers":0,"awacs":0,"reconnaissance":0,"transport":0,"bombers":0,"drones":0,"unknown":2,"totalAircraft":2,"destroyers":0,"frigates":0,"carriers":0,"submarines":0,"patrol":0,"auxiliaryVessels":0,"totalVessels":0,"byOperator":{"unknown":2},"postureLevel":"normal","strikeCapable":false,"trend":"stable","changePercent":0,"summary":"2 other","headline":"Normal activity - South China Sea","centerLat":15,"centerLon":113,"bounds":{"north":25,"south":5,"east":121,"west":105}},{"theaterId":"east-med-theater","theaterName":"Eastern Mediterranean","shortName":"E.MED","targetNation":null,"fighters":0,"tankers":0,"awacs":0,"reconnaissance":0,"transport":0,"bombers":0,"drones":0,"unknown":5,"totalAircraft":5,"destroyers":0,"frigates":0,"carriers":0,"submarines":0,"patrol":0,"auxiliaryVessels":0,"totalVessels":0,"byOperator":{"unknown":5},"postureLevel":"elevated","strikeCapable":false,"trend":"stable","changePercent":0,"summary":"5 other","headline":"Elevated military activity - Eastern Mediterranean","centerLat":35,"centerLon":31,"bounds":{"north":37,"south":33,"east":37,"west":25}},{"theaterId":"israel-gaza-theater","theaterName":"Israel/Gaza","shortName":"GAZA","targetNation":"Gaza","fighters":0,"tankers":0,"awacs":0,"reconnaissance":0,"transport":0,"bombers":0,"drones":0,"unknown":0,"totalAircraft":0,"destroyers":0,"frigates":0,"carriers":0,"submarines":0,"patrol":0,"auxiliaryVessels":0,"totalVessels":0,"byOperator":{},"postureLevel":"normal","strikeCapable":false,"trend":"stable","changePercent":0,"summary":"No military aircraft","headline":"Normal activity - Israel/Gaza","centerLat":31,"centerLon":34.5,"bounds":{"north":33,"south":29,"east":36,"west":33}},{"theaterId":"yemen-redsea-theater","theaterName":"Yemen/Red Sea","shortName":"RED SEA","targetNation":"Yemen","fighters":0,"tankers":0,"awacs":0,"reconnaissance":0,"transport":0,"bombers":0,"drones":0,"unknown":0,"totalAircraft":0,"destroyers":0,"frigates":0,"carriers":0,"submarines":0,"patrol":0,"auxiliaryVessels":0,"totalVessels":0,"byOperator":{},"postureLevel":"normal","strikeCapable":false,"trend":"stable","changePercent":0,"summary":"No military aircraft","headline":"Normal activity - Yemen/Red Sea","centerLat":16.5,"centerLon":43,"bounds":{"north":22,"south":11,"east":54,"west":32}}],"totalFlights":349,"timestamp":"2026-03-11T23:00:30.050Z","cached":false,"source":"opensky"},"expiresAt":1773356430050},"theater-posture:backup:v4":{"value":{"postures":[{"theaterId":"iran-theater","theaterName":"Iran Theater","shortName":"IRAN","targetNation":"Iran","fighters":0,"tankers":0,"awacs":0,"reconnaissance":0,"transport":0,"bombers":0,"drones":0,"unknown":4,"totalAircraft":4,"destroyers":0,"frigates":0,"carriers":0,"submarines":0,"patrol":0,"auxiliaryVessels":0,"totalVessels":0,"byOperator":{"unknown":4},"postureLevel":"normal","strikeCapable":false,"trend":"stable","changePercent":0,"summary":"4 other","headline":"Normal activity - Iran Theater","centerLat":31,"centerLon":47.5,"bounds":{"north":42,"south":20,"east":65,"west":30}},{"theaterId":"taiwan-theater","theaterName":"Taiwan Strait","shortName":"TAIWAN","targetNation":"Taiwan","fighters":0,"tankers":0,"awacs":0,"reconnaissance":0,"transport":0,"bombers":0,"drones":0,"unknown":0,"totalAircraft":0,"destroyers":0,"frigates":0,"carriers":0,"submarines":0,"patrol":0,"auxiliaryVessels":0,"totalVessels":0,"byOperator":{},"postureLevel":"normal","strikeCapable":false,"trend":"stable","changePercent":0,"summary":"No military aircraft","headline":"Normal activity - Taiwan Strait","centerLat":24,"centerLon":122.5,"bounds":{"north":30,"south":18,"east":130,"west":115}},{"theaterId":"baltic-theater","theaterName":"Baltic Theater","shortName":"BALTIC","targetNation":null,"fighters":0,"tankers":0,"awacs":0,"reconnaissance":0,"transport":0,"bombers":0,"drones":0,"unknown":2,"totalAircraft":2,"destroyers":0,"frigates":0,"carriers":0,"submarines":0,"patrol":0,"auxiliaryVessels":0,"totalVessels":0,"byOperator":{"unknown":2},"postureLevel":"normal","strikeCapable":false,"trend":"stable","changePercent":0,"summary":"2 other","headline":"Normal activity - Baltic Theater","centerLat":58.5,"centerLon":21,"bounds":{"north":65,"south":52,"east":32,"west":10}},{"theaterId":"blacksea-theater","theaterName":"Black Sea","shortName":"BLACK SEA","targetNation":null,"fighters":0,"tankers":0,"awacs":0,"reconnaissance":0,"transport":0,"bombers":0,"drones":0,"unknown":1,"totalAircraft":1,"destroyers":0,"frigates":0,"carriers":0,"submarines":0,"patrol":0,"auxiliaryVessels":0,"totalVessels":0,"byOperator":{"unknown":1},"postureLevel":"normal","strikeCapable":false,"trend":"stable","changePercent":0,"summary":"1 other","headline":"Normal activity - Black Sea","centerLat":44,"centerLon":34,"bounds":{"north":48,"south":40,"east":42,"west":26}},{"theaterId":"korea-theater","theaterName":"Korean Peninsula","shortName":"KOREA","targetNation":"North Korea","fighters":0,"tankers":0,"awacs":0,"reconnaissance":0,"transport":0,"bombers":0,"drones":0,"unknown":5,"totalAircraft":5,"destroyers":0,"frigates":0,"carriers":0,"submarines":0,"patrol":0,"auxiliaryVessels":0,"totalVessels":0,"byOperator":{"unknown":5},"postureLevel":"elevated","strikeCapable":false,"trend":"stable","changePercent":0,"summary":"5 other","headline":"Elevated military activity - Korean Peninsula","centerLat":38,"centerLon":128,"bounds":{"north":43,"south":33,"east":132,"west":124}},{"theaterId":"south-china-sea","theaterName":"South China Sea","shortName":"SCS","targetNation":null,"fighters":0,"tankers":0,"awacs":0,"reconnaissance":0,"transport":0,"bombers":0,"drones":0,"unknown":2,"totalAircraft":2,"destroyers":0,"frigates":0,"carriers":0,"submarines":0,"patrol":0,"auxiliaryVessels":0,"totalVessels":0,"byOperator":{"unknown":2},"postureLevel":"normal","strikeCapable":false,"trend":"stable","changePercent":0,"summary":"2 other","headline":"Normal activity - South China Sea","centerLat":15,"centerLon":113,"bounds":{"north":25,"south":5,"east":121,"west":105}},{"theaterId":"east-med-theater","theaterName":"Eastern Mediterranean","shortName":"E.MED","targetNation":null,"fighters":0,"tankers":0,"awacs":0,"reconnaissance":0,"transport":0,"bombers":0,"drones":0,"unknown":5,"totalAircraft":5,"destroyers":0,"frigates":0,"carriers":0,"submarines":0,"patrol":0,"auxiliaryVessels":0,"totalVessels":0,"byOperator":{"unknown":5},"postureLevel":"elevated","strikeCapable":false,"trend":"stable","changePercent":0,"summary":"5 other","headline":"Elevated military activity - Eastern Mediterranean","centerLat":35,"centerLon":31,"bounds":{"north":37,"south":33,"east":37,"west":25}},{"theaterId":"israel-gaza-theater","theaterName":"Israel/Gaza","shortName":"GAZA","targetNation":"Gaza","fighters":0,"tankers":0,"awacs":0,"reconnaissance":0,"transport":0,"bombers":0,"drones":0,"unknown":0,"totalAircraft":0,"destroyers":0,"frigates":0,"carriers":0,"submarines":0,"patrol":0,"auxiliaryVessels":0,"totalVessels":0,"byOperator":{},"postureLevel":"normal","strikeCapable":false,"trend":"stable","changePercent":0,"summary":"No military aircraft","headline":"Normal activity - Israel/Gaza","centerLat":31,"centerLon":34.5,"bounds":{"north":33,"south":29,"east":36,"west":33}},{"theaterId":"yemen-redsea-theater","theaterName":"Yemen/Red Sea","shortName":"RED SEA","targetNation":"Yemen","fighters":0,"tankers":0,"awacs":0,"reconnaissance":0,"transport":0,"bombers":0,"drones":0,"unknown":0,"totalAircraft":0,"destroyers":0,"frigates":0,"carriers":0,"submarines":0,"patrol":0,"auxiliaryVessels":0,"totalVessels":0,"byOperator":{},"postureLevel":"normal","strikeCapable":false,"trend":"stable","changePercent":0,"summary":"No military aircraft","headline":"Normal activity - Yemen/Red Sea","centerLat":16.5,"centerLon":43,"bounds":{"north":22,"south":11,"east":54,"west":32}}],"totalFlights":349,"timestamp":"2026-03-11T23:00:30.050Z","cached":false,"source":"opensky"},"expiresAt":1773874830050},"unhcr:population:v2":{"value":{"success":true,"year":2025,"globalTotals":{"refugees":30490994,"asylumSeekers":8414659,"idps":63852580,"stateless":4431462,"total":107189695},"countries":[{"code":"-","name":"-","refugees":30490994,"asylumSeekers":8414659,"idps":63852580,"stateless":4431462,"totalDisplaced":107189695,"hostRefugees":30490994,"hostAsylumSeekers":8414659,"hostTotal":38905653}],"topFlows":[{"originCode":"-","originName":"-","asylumCode":"-","asylumName":"-","refugees":30490994}],"cached_at":"2026-03-11T22:30:32.128Z"},"expiresAt":1773354632128},"climate:anomalies:v1":{"value":{"success":true,"anomalies":[{"zone":"Ukraine","lat":48.4,"lon":31.2,"tempDelta":5.7,"precipDelta":-1.9,"severity":"extreme","type":"warm","period":"2026-02-09 to 2026-03-11"},{"zone":"Middle East","lat":33,"lon":44,"tempDelta":-3.2,"precipDelta":0,"severity":"moderate","type":"cold","period":"2026-02-09 to 2026-03-11"},{"zone":"Sahel","lat":14,"lon":0,"tempDelta":3.7,"precipDelta":0,"severity":"moderate","type":"warm","period":"2026-02-09 to 2026-03-11"},{"zone":"Horn of Africa","lat":8,"lon":42,"tempDelta":0,"precipDelta":0.1,"severity":"normal","type":"cold","period":"2026-02-09 to 2026-03-11"},{"zone":"South Asia","lat":25,"lon":78,"tempDelta":5.7,"precipDelta":-0.1,"severity":"extreme","type":"warm","period":"2026-02-09 to 2026-03-11"},{"zone":"California","lat":36.8,"lon":-119.4,"tempDelta":1.5,"precipDelta":-4.3,"severity":"normal","type":"warm","period":"2026-02-09 to 2026-03-11"},{"zone":"Amazon","lat":-3.4,"lon":-60,"tempDelta":0.1,"precipDelta":2.3,"severity":"normal","type":"warm","period":"2026-02-09 to 2026-03-11"},{"zone":"Australia","lat":-25,"lon":134,"tempDelta":1,"precipDelta":-4.1,"severity":"normal","type":"warm","period":"2026-02-09 to 2026-03-11"},{"zone":"Mediterranean","lat":38,"lon":20,"tempDelta":0.4,"precipDelta":-2.4,"severity":"normal","type":"warm","period":"2026-02-09 to 2026-03-11"},{"zone":"Taiwan Strait","lat":24,"lon":120,"tempDelta":-1.1,"precipDelta":-1.1,"severity":"normal","type":"cold","period":"2026-02-09 to 2026-03-11"},{"zone":"Myanmar","lat":19.8,"lon":96.7,"tempDelta":1.4,"precipDelta":-0.3,"severity":"normal","type":"warm","period":"2026-02-09 to 2026-03-11"},{"zone":"Central Africa","lat":4,"lon":22,"tempDelta":1.6,"precipDelta":-1.5,"severity":"normal","type":"warm","period":"2026-02-09 to 2026-03-11"},{"zone":"Southern Africa","lat":-25,"lon":28,"tempDelta":-2.4,"precipDelta":0.7,"severity":"normal","type":"cold","period":"2026-02-09 to 2026-03-11"},{"zone":"Central Asia","lat":42,"lon":65,"tempDelta":-2.5,"precipDelta":-0.5,"severity":"normal","type":"cold","period":"2026-02-09 to 2026-03-11"},{"zone":"Caribbean","lat":19,"lon":-72,"tempDelta":0.5,"precipDelta":2.2,"severity":"normal","type":"warm","period":"2026-02-09 to 2026-03-11"}],"timestamp":"2026-03-11T22:30:32.763Z"},"expiresAt":1773289832764},"baseline:military_flights:global:3:3":{"value":{"mean":0,"m2":0,"sampleCount":8,"lastUpdated":"2026-03-11T23:06:27.741Z"},"expiresAt":1781046387741},"baseline:vessels:global:3:3":{"value":{"mean":0,"m2":0,"sampleCount":8,"lastUpdated":"2026-03-11T23:06:27.741Z"},"expiresAt":1781046387741},"baseline:news:global:3:3":{"value":{"mean":295,"m2":0,"sampleCount":7,"lastUpdated":"2026-03-11T23:04:16.676Z"},"expiresAt":1781046256677},"coingecko:v2:qqysrm":{"value":{"body":"[{\"id\":\"bitcoin\",\"symbol\":\"btc\",\"name\":\"Bitcoin\",\"image\":\"https://coin-images.coingecko.com/coins/images/1/large/bitcoin.png?1696501400\",\"current_price\":70475,\"market_cap\":1409555277975,\"market_cap_rank\":1,\"fully_diluted_valuation\":1409555277975,\"total_volume\":48398696389,\"high_24h\":71230,\"low_24h\":69034,\"price_change_24h\":733.91,\"price_change_percentage_24h\":1.05234,\"market_cap_change_24h\":14748151145,\"market_cap_change_percentage_24h\":1.05736,\"circulating_supply\":20000962.0,\"total_supply\":20000962.0,\"max_supply\":21000000.0,\"ath\":126080,\"ath_change_percentage\":-44.10321,\"ath_date\":\"2025-10-06T18:57:42.558Z\",\"atl\":67.81,\"atl_change_percentage\":103831.05568,\"atl_date\":\"2013-07-06T00:00:00.000Z\",\"roi\":null,\"last_updated\":\"2026-03-11T23:07:24.665Z\",\"sparkline_in_7d\":{\"price\":[73247.3770874455,73648.64917933119,73669.77886917477,73161.480111882,73332.92473534899,72719.81406521072,72718.88789125846,72792.80519135129,72543.97464203274,72477.59891992927,72504.38750029696,72826.29275269817,72398.01904819139,72558.8073025577,72058.09213017001,72340.2322743391,72589.83515692299,73406.86988902156,72896.38098082828,72956.71174985172,72488.15920985509,72619.89526730274,71594.57304247013,71267.70706478962,70744.21599700359,70979.16536779414,70953.80913795276,71265.64088358545,71155.32063355974,71233.21871236167,70878.27262880845,70961.67314503502,71238.28505185546,71240.53565521113,71066.03139446002,70599.99227022535,70435.78630865278,70622.50345483121,71059.3355218869,70751.65437144341,70561.77286389082,70527.98604211934,70196.22489571887,69955.86385344793,69913.66023265437,68403.27260608313,68534.06273037645,68455.86235282138,67974.71278155119,68225.34836804391,68136.5508355917,68122.78900063572,68298.31021327554,68413.33201551982,68133.41234390924,68314.63160306022,68275.39003217602,68341.33395711421,68117.04958832913,68069.33206683511,67996.84558525002,67691.48809641342,67834.614924263,67765.61835133213,67998.52815434017,67873.1587799662,68013.71562200207,67991.10356990024,67916.10328917604,68019.16019187449,67899.15084849336,67801.01632269858,67785.60887414815,67568.88224162976,67094.31199504284,67399.62925530928,67439.67756365686,67249.11359189247,67267.81296868966,67197.22956158094,67281.09358801546,66935.58846870842,67017.06275576772,66636.37298484836,67150.76620090878,67167.12682747483,67317.67908156205,67526.04081531901,67722.3906207067,67884.75605610275,67514.2500672652,67323.5700408118,67248.51952009877,67321.59318610797,67198.71988114901,66867.13985743086,67030.47416665868,66847.67389482637,67297.5502613865,67254.4625303784,66962.49688469661,66243.61118027143,65962.93555768127,66369.29068703564,66204.59808090409,66577.38675273205,67197.08091007096,67143.7362955291,67860.78727055466,67277.5702394931,67544.00250260242,67799.38632343274,68007.33535432584,67608.59266938583,67772.83349716141,68149.84647806143,69019.89906120331,69151.00637818531,68865.00153447736,68967.55696578688,68586.1322721637,68382.37443771512,69013.32134406736,69011.53178113446,68985.56728807802,68646.004299425,68420.96624019857,69123.81521690538,69316.07332742578,70275.63359459382,69449.86201997902,70044.90067885906,69961.99530664866,69914.59605617836,70419.16601230872,70662.68348732492,71056.89908137723,70770.46303081533,70612.08411027637,70533.41432323735,69920.65656894125,71473.0344724545,71384.61842595358,71230.96703062182,70876.32886179285,70016.60740710664,70037.03937424635,70257.54187441531,69784.40516943767,69707.35896547118,69928.9163122041,70057.98541416498,70080.11397075102,69763.51651372905,69557.75379754089,70155.65059687756,69538.60953568769,69949.21090595724,69654.51423342456,69624.47487489082,69463.49540861479,69611.218091922,69180.65971302507,69350.52650059077,70175.84884647054,70623.27716209645,70259.38523711842,70564.76764531482,70773.23922506295]},\"price_change_percentage_24h_in_currency\":1.052344215802349},{\"id\":\"ethereum\",\"symbol\":\"eth\",\"name\":\"Ethereum\",\"image\":\"https://coin-images.coingecko.com/coins/images/279/large/ethereum.png?1696501628\",\"current_price\":2063.76,\"market_cap\":249078562119,\"market_cap_rank\":2,\"fully_diluted_valuation\":249078562119,\"total_volume\":18926196659,\"high_24h\":2082.55,\"low_24h\":2010.47,\"price_change_24h\":30.01,\"price_change_percentage_24h\":1.47554,\"market_cap_change_24h\":3783436981,\"market_cap_change_percentage_24h\":1.5424,\"circulating_supply\":120692001.7320773,\"total_supply\":120692001.7320773,\"max_supply\":null,\"ath\":4946.05,\"ath_change_percentage\":-58.27448,\"ath_date\":\"2025-08-24T19:21:03.333Z\",\"atl\":0.432979,\"atl_change_percentage\":476543.2174,\"atl_date\":\"2015-10-20T00:00:00.000Z\",\"roi\":{\"times\":38.14947003477403,\"currency\":\"btc\",\"percentage\":3814.947003477403},\"last_updated\":\"2026-03-11T23:07:24.691Z\",\"sparkline_in_7d\":{\"price\":[2147.0371850591255,2162.208620313557,2179.3034097539403,2155.6855981582416,2150.7279943966005,2132.1752731699717,2127.5395593313337,2128.9595318254815,2114.0835806007112,2121.0508084832863,2120.114262196051,2137.4506740783195,2118.757947320142,2128.4988410038313,2103.1852983306158,2117.1768323491838,2124.9191886421886,2156.914380289229,2138.0647220077653,2139.533923820458,2118.5275661945584,2118.652533203664,2084.259312311558,2080.834129319046,2059.6879721491946,2075.918386887758,2075.1310717157153,2093.0704153795728,2080.8081782518916,2081.3964578660493,2073.044331238617,2074.5370717489996,2087.5727549691305,2083.5272514680078,2083.1395882671072,2069.5312839432972,2068.8448704797224,2074.749060715415,2082.7662883444423,2075.3711533438845,2059.3418197800333,2062.9849863148424,2050.593709118484,2049.2665562967377,2017.047163266689,1981.7821985199919,1977.6239796025125,1971.1851533662496,1967.4604619146398,1974.9148054972716,1984.1726116377824,1980.3531024762194,1983.9366787606157,1987.9279378264857,1978.7065114540444,1981.82517686465,1981.0883515357011,1983.2493666107002,1980.3151370198484,1975.5708491871005,1977.9373509618629,1972.2527459764772,1982.1163284513907,1977.449056676776,1986.5744622657578,1984.043931346829,1988.8070268191993,1982.2405623561851,1981.524750798637,1987.1403216717051,1981.3633235211314,1977.3931775392205,1977.3105240034927,1971.2613780400052,1954.9555284757218,1966.5199444615084,1970.2353198220776,1965.6574137467508,1969.775618066929,1969.0970457507176,1968.6342533987108,1941.9691280509335,1947.7447665309178,1937.7159092514803,1947.8671040836753,1947.6887595781561,1955.2531666894365,1958.9652030479995,1963.7105096066002,1972.4307037745152,1951.615372876082,1946.244884185458,1944.2226347666904,1945.0765585891827,1942.2629549786254,1936.4851617249585,1935.4554405489778,1930.9906724595066,1963.9918225562003,1958.6389000245022,1953.2224918205902,1942.5448931227684,1936.2658470355996,1951.4435186053672,1945.5371408394353,1960.0152296663668,1976.8422413903531,1977.9293266921104,2009.4386314203327,1985.5864913026335,1983.4727446831137,1996.4047771053995,2004.6862923833905,1994.8565752987513,1993.1537304203491,2002.3519904163948,2018.4234667845765,2022.0273158418147,2023.727110264863,2027.6122004112167,2016.9215667503627,2012.2006940712574,2035.2294023759414,2027.417820655692,2029.5061046155902,2002.5111868317822,1992.9224687558517,2014.9606381771744,2020.2412359714224,2041.9620336639148,2027.290800327835,2044.9848041877103,2043.4333397321554,2043.7913456254316,2051.9370052247164,2056.987998806003,2068.3484058956633,2062.6383638388043,2061.7502173274615,2050.2780038484193,2033.5269787249406,2077.1179439765624,2079.8438290631575,2080.7140778247085,2071.738833960878,2039.6262830461121,2036.703445059322,2042.2714202183072,2029.572704906523,2027.7078323110989,2036.151719839931,2037.8774737132821,2036.2681313312455,2026.0814254963498,2021.125015041226,2039.3472493697946,2014.7978900240837,2024.2784556283057,2012.687488636196,2022.908186198996,2017.0018672160131,2028.6906951407427,2018.1140036653921,2023.4629394398958,2050.849093507279,2064.125686927166,2050.374673174742,2066.878860447783,2068.064535201132]},\"price_change_percentage_24h_in_currency\":1.4755372863616416},{\"id\":\"solana\",\"symbol\":\"sol\",\"name\":\"Solana\",\"image\":\"https://coin-images.coingecko.com/coins/images/4128/large/solana.png?1718769756\",\"current_price\":87.12,\"market_cap\":49752775476,\"market_cap_rank\":7,\"fully_diluted_valuation\":49752776715,\"total_volume\":3996629724,\"high_24h\":87.83,\"low_24h\":84.52,\"price_change_24h\":1.5,\"price_change_percentage_24h\":1.75106,\"market_cap_change_24h\":890058376,\"market_cap_change_percentage_24h\":1.82155,\"circulating_supply\":571113896.0153779,\"total_supply\":571113910.2348504,\"max_supply\":null,\"ath\":293.31,\"ath_change_percentage\":-70.29673,\"ath_date\":\"2025-01-19T11:15:27.957Z\",\"atl\":0.500801,\"atl_change_percentage\":17296.77373,\"atl_date\":\"2020-05-11T19:35:23.449Z\",\"roi\":null,\"last_updated\":\"2026-03-11T23:06:52.690Z\",\"sparkline_in_7d\":{\"price\":[92.30576010703456,93.41305666144846,93.11422854724556,92.37827546561722,91.36001226024793,90.96286116719976,90.91989137857524,89.92332928141414,90.19284886883679,90.01079866516491,90.42774912651967,90.17558926402215,90.86575457816525,90.07177641389886,90.60961053388469,91.20666161875315,92.67681751038538,91.83821926110274,92.06260742077046,90.93449068204696,90.69683737551506,89.5366198400881,88.94165878808832,88.17051990328366,88.70752515773282,88.83632803937107,89.21416840075608,89.12039016719704,89.22208477654938,88.73214898994317,88.78478143621474,89.12487519637786,88.41425588156598,88.39706980639205,88.08653355759078,87.84462005599399,88.11923713824176,88.7145323858682,88.3373018772827,87.46621463816895,87.72112332040224,87.22492084288791,86.45933785914367,85.99644350471316,84.31417397485039,84.57132658720931,84.61149698599007,84.19121159827199,85.38465205788225,85.25121034103242,85.04314755041784,84.70755114868109,84.97608148383881,84.68229429850666,84.76053282488452,84.76498615704072,84.55569004818933,84.47135112614036,84.34502238480083,84.39881743892514,84.05802286095494,84.29216004356432,84.40319710054177,84.58990211534261,84.510367033486,84.74105966497658,84.32261519392382,84.29164357076957,84.2273555825573,83.73958265316065,83.59184727308444,83.78326905074783,83.39804526157673,82.5089835188689,83.01507528804385,83.1516952467228,83.00001539850025,83.20218626877367,83.04383037176176,83.03314226011524,82.45167996585833,82.39122484676778,82.0170409407218,82.55723878360611,82.40026905411165,82.90511272736303,83.04361334421459,83.20440553477059,83.69057562223436,82.82945735808882,82.321445058237,82.02690719748348,82.22053120919236,81.99708260109466,81.47764605257376,81.64034646457729,81.60486023938864,82.40395093858264,82.43286392749985,82.16500254434592,82.05769444614864,81.62170106945176,82.40643105840705,82.33585880867332,82.721523260208,83.10797565270069,83.42568608838516,84.30152090393771,83.21794131161106,83.14706819413303,83.66903694025524,84.10596210932933,83.67947579595958,83.62870122069073,83.98553173608798,85.19402602928692,85.36037166134993,85.08667240698253,85.16989706384855,84.99638460561125,85.2129612845799,86.01610835738464,85.471161325024,86.02224059459134,85.72009775995603,84.92841108438161,85.60931309047548,85.7160597975056,86.6028050640728,85.62409910490162,86.39335718526212,86.38355282154046,86.32973566209891,86.63102515046928,86.72250435383914,87.23450533115489,87.09611445971461,86.82493315950379,86.67382258113517,86.2688812199773,87.67752492578181,88.07957267229472,88.44715136152152,87.9892790561503,86.28497370179785,86.01475926174022,86.19782305947425,85.64478790283205,85.52426044782896,85.80210497143722,86.05377201186482,86.09356296075154,85.79588400638684,85.62100557697109,86.62844863383354,85.76283346359764,86.0040099479934,85.47523841394978,85.39256288512959,84.96847953356534,85.36348713374595,84.5221827774949,85.15417133651708,85.87966323955132,86.65099930549496,85.36900672038779,86.42810928768714,87.26529452317321]},\"price_change_percentage_24h_in_currency\":1.7510609595868725}]","status":200},"expiresAt":1773270583200}}